httpx_impersonate/__init__.py
httpx_impersonate/ciphers.py
httpx_impersonate/headers.py
httpx_impersonate-0.1.0.dist-info/LICENSE.md
httpx_impersonate-0.1.0.dist-info/METADATA
httpx_impersonate-0.1.0.dist-info/WHEEL
httpx_impersonate-0.1.0.dist-info/top_level.txt
httpx_impersonate-0.1.0.dist-info/RECORD
